memory_efficient_attention/__init__.py
memory_efficient_attention/attention_jax.py
memory_efficient_attention/attention_torch.py
memory_efficient_attention/utils.py
test/__init__.py
test/test_computation.py
memory_efficient_attention-0.1.3.dist-info/METADATA
memory_efficient_attention-0.1.3.dist-info/WHEEL
memory_efficient_attention-0.1.3.dist-info/top_level.txt
memory_efficient_attention-0.1.3.dist-info/RECORD
